model_ELISA/__init__.py
model_ELISA/model_ELISA_gui.py
model_ELISA-0.1.3.dist-info/LICENSE
model_ELISA-0.1.3.dist-info/METADATA
model_ELISA-0.1.3.dist-info/WHEEL
model_ELISA-0.1.3.dist-info/top_level.txt
model_ELISA-0.1.3.dist-info/RECORD
