Metadata-Version: 2.1
Name: model_ELISA
Version: 0.1.3
Summary: A GUI to simulate the direct ELISA model
Home-page: https://github.com/kml5gb/model_ELISA
Author: Kelsey Leong
Author-email: kml5gb@uw.edu
Classifier: Programming Language :: Python :: 3
Classifier: License :: OSI Approved :: MIT License
Classifier: Operating System :: OS Independent
License-File: LICENSE
Requires-Dist: numpy
Requires-Dist: matplotlib
Requires-Dist: tellurium
